aprsd_assistant_plugin/__about__.py
aprsd_assistant_plugin/__init__.py
aprsd_assistant_plugin/_plugin.py
aprsd_assistant_plugin/conf/__init__.py
aprsd_assistant_plugin/conf/main.py
aprsd_assistant_plugin-0.0.3.dist-info/METADATA
aprsd_assistant_plugin-0.0.3.dist-info/WHEEL
aprsd_assistant_plugin-0.0.3.dist-info/licenses/LICENSE.txt
aprsd_assistant_plugin-0.0.3.dist-info/RECORD
