Metadata-Version: 2.3
Name: aprsd-assistant-plugin
Version: 0.0.3
Summary: APRSd plugin for hosting the APRS Assistant chatbot (aprs-assistant)
Project-URL: Documentation, https://github.com/afourney/aprsd-assistant-plugin#readme
Project-URL: Homepage, https://github.com/afourney/aprsd-assistant-plugin
Project-URL: Source, https://github.com/afourney/aprsd-assistant-plugin
Project-URL: Issues, https://github.com/afourney/aprsd-assistant-plugin/issues
Author-email: Adam Fourney <adam.fourney@gmail.com>
License-Expression: MIT
License-File: LICENSE.txt
Classifier: Development Status :: 4 - Beta
Classifier: Programming Language :: Python
Classifier: Programming Language :: Python :: 3.8
Classifier: Programming Language :: Python :: 3.9
Classifier: Programming Language :: Python :: 3.10
Classifier: Programming Language :: Python :: 3.11
Classifier: Programming Language :: Python :: 3.12
Classifier: Programming Language :: Python :: Implementation :: CPython
Classifier: Programming Language :: Python :: Implementation :: PyPy
Requires-Python: >=3.8
Requires-Dist: aprs-assistant
Requires-Dist: aprsd
